Workbook

Sheet Supuestos
A1: WALKAN — Supuestos del modelo de recuperación de inversión
A2: Celdas amarillas = editables. Óptica: Walkan (negocio SaaS). Moneda: CLP.
A4: PLANES (CLP/mes)
A5: Precio Kiosko | B5: 9990
A6: Precio Minimarket | B6: 19990
A7: Precio Minisúper | B7: 34990
A9: MEZCLA DE CLIENTES POR PLAN
A10: % Kiosko | B10: 0.5
A11: % Minimarket | B11: 0.35
A12: % Minisúper | B12: 0.15
A13: Suma (debe ser 100%) | B13: =B10+B11+B12 -> 1
A14: ARPU (ingreso medio por cliente/mes) | B14: =B5*B10+B6*B11+B7*B12 -> 17240 | C14: Promedio ponderado por la mezcla
A16: INVERSIÓN INICIAL — DESARROLLO
A17: Integrantes | B17: 2
A18: Meses de desarrollo | B18: 4
A19: Sueldo mensual (ref. mercado) | B19: 1000000
A20: Inversión en desarrollo | B20: =B17*B18*B19 -> 8000000 | C20: Valorización de horas del equipo (supuesto)
A22: COSTOS
A23: Hardware por caja regalada | B23: 80000 | C23: TV Box + impresora térmica + lector
A24: VPS mensual | B24: 50000
A25: Dominio anual | B25: 12000
A26: Opex mensual (VPS + dominio) | B26: =B24+B25/12 -> 51000
A27: Comisión Flow | B27: 0.0289 | C27: Por transacción, sobre el cobro
A28: IVA | B28: 0.19
A29: Comisión Flow efectiva (c/IVA) | B29: =B27*(1+B28) -> 0.034391
A31: CRECIMIENTO (clientes nuevos por mes)
A32: Escenario conservador | B32: 1
A33: Escenario realista | B33: 3
A34: Escenario optimista | B34: 6
A35: Tope de clientes (1ª caja incluida) | B35: 100
A36: Horizonte del modelo (meses) | B36: 60

Sheet Proyeccion
A1: WALKAN — Proyección mensual de flujo (óptica Walkan)
A2: Mes 0 = inversión inicial en desarrollo. Cifras en CLP. | B2: CONSERVADOR | K2: REALISTA | T2: OPTIMISTA
A3: Mes | B3: Nuevos | C3: Activos | D3: Ingresos | E3: Comisión Flow | F3: Hardware | G3: Opex | H3: Flujo neto | I3: Flujo acumulado | K3: Nuevos | L3: Activos | M3: Ingresos | N3: Comisión Flow | O3: Hardware | P3: Opex | Q3: Flujo neto | R3: Flujo acumulado | T3: Nuevos | U3: Activos | V3: Ingresos | W3: Comisión Flow | X3: Hardware | Y3: Opex | Z3: Flujo neto | AA3: Flujo acumulado
A4: 0 | B4: 0 | C4: 0 | D4: 0 | E4: 0 | F4: 0 | G4: 0 | H4: =-Supuestos!$B$20 -> -8000000 | I4: =H4 -> -8000000 | K4: 0 | L4: 0 | M4: 0 | N4: 0 | O4: 0 | P4: 0 | Q4: =-Supuestos!$B$20 -> -8000000 | R4: =Q4 -> -8000000 | T4: 0 | U4: 0 | V4: 0 | W4: 0 | X4: 0 | Y4: 0 | Z4: =-Supuestos!$B$20 -> -8000000 | AA4: =Z4 -> -8000000
A5: 1 | B5: =MIN(Supuestos!$B$32, Supuestos!$B$35-C4) -> 1 | C5: =C4+B5 -> 1 | D5: =C5*Supuestos!$B$14 -> 17240 | E5: =D5*Supuestos!$B$29 -> 592.90084 | F5: =B5*Supuestos!$B$23 -> 80000 | G5: =Supuestos!$B$26 -> 51000 | H5: =D5-E5-F5-G5 -> -114352.9 | I5: =I4+H5 -> -8114352.9 | K5: =MIN(Supuestos!$B$33, Supuestos!$B$35-L4) -> 3 | L5: =L4+K5 -> 3 | M5: =L5*Supuestos!$B$14 -> 51720 | N5: =M5*Supuestos!$B$29 -> 1778.7025 | O5: =K5*Supuestos!$B$23 -> 240000 | P5: =Supuestos!$B$26 -> 51000 | Q5: =M5-N5-O5-P5 -> -241058.7 | R5: =R4+Q5 -> -8241058.7 | T5: =MIN(Supuestos!$B$34, Supuestos!$B$35-U4) -> 6 | U5: =U4+T5 -> 6 | V5: =U5*Supuestos!$B$14 -> 103440 | W5: =V5*Supuestos!$B$29 -> 3557.405 | X5: =T5*Supuestos!$B$23 -> 480000 | Y5: =Supuestos!$B$26 -> 51000 | Z5: =V5-W5-X5-Y5 -> -431117.41 | AA5: =AA4+Z5 -> -8431117.4
A6: 2 | B6: =MIN(Supuestos!$B$32, Supuestos!$B$35-C5) -> 1 | C6: =C5+B6 -> 2 | D6: =C6*Supuestos!$B$14 -> 34480 | E6: =D6*Supuestos!$B$29 -> 1185.8017 | F6: =B6*Supuestos!$B$23 -> 80000 | G6: =Supuestos!$B$26 -> 51000 | H6: =D6-E6-F6-G6 -> -97705.802 | I6: =I5+H6 -> -8212058.7 | K6: =MIN(Supuestos!$B$33, Supuestos!$B$35-L5) -> 3 | L6: =L5+K6 -> 6 | M6: =L6*Supuestos!$B$14 -> 103440 | N6: =M6*Supuestos!$B$29 -> 3557.405 | O6: =K6*Supuestos!$B$23 -> 240000 | P6: =Supuestos!$B$26 -> 51000 | Q6: =M6-N6-O6-P6 -> -191117.41 | R6: =R5+Q6 -> -8432176.1 | T6: =MIN(Supuestos!$B$34, Supuestos!$B$35-U5) -> 6 | U6: =U5+T6 -> 12 | V6: =U6*Supuestos!$B$14 -> 206880 | W6: =V6*Supuestos!$B$29 -> 7114.8101 | X6: =T6*Supuestos!$B$23 -> 480000 | Y6: =Supuestos!$B$26 -> 51000 | Z6: =V6-W6-X6-Y6 -> -331234.81 | AA6: =AA5+Z6 -> -8762352.2
A7: 3 | B7: =MIN(Supuestos!$B$32, Supuestos!$B$35-C6) -> 1 | C7: =C6+B7 -> 3 | D7: =C7*Supuestos!$B$14 -> 51720 | E7: =D7*Supuestos!$B$29 -> 1778.7025 | F7: =B7*Supuestos!$B$23 -> 80000 | G7: =Supuestos!$B$26 -> 51000 | H7: =D7-E7-F7-G7 -> -81058.703 | I7: =I6+H7 -> -8293117.4 | K7: =MIN(Supuestos!$B$33, Supuestos!$B$35-L6) -> 3 | L7: =L6+K7 -> 9 | M7: =L7*Supuestos!$B$14 -> 155160 | N7: =M7*Supuestos!$B$29 -> 5336.1076 | O7: =K7*Supuestos!$B$23 -> 240000 | P7: =Supuestos!$B$26 -> 51000 | Q7: =M7-N7-O7-P7 -> -141176.11 | R7: =R6+Q7 -> -8573352.2 | T7: =MIN(Supuestos!$B$34, Supuestos!$B$35-U6) -> 6 | U7: =U6+T7 -> 18 | V7: =U7*Supuestos!$B$14 -> 310320 | W7: =V7*Supuestos!$B$29 -> 10672.215 | X7: =T7*Supuestos!$B$23 -> 480000 | Y7: =Supuestos!$B$26 -> 51000 | Z7: =V7-W7-X7-Y7 -> -231352.22 | AA7: =AA6+Z7 -> -8993704.4
A8: 4 | B8: =MIN(Supuestos!$B$32, Supuestos!$B$35-C7) -> 1 | C8: =C7+B8 -> 4 | D8: =C8*Supuestos!$B$14 -> 68960 | E8: =D8*Supuestos!$B$29 -> 2371.6034 | F8: =B8*Supuestos!$B$23 -> 80000 | G8: =Supuestos!$B$26 -> 51000 | H8: =D8-E8-F8-G8 -> -64411.603 | I8: =I7+H8 -> -8357529 | K8: =MIN(Supuestos!$B$33, Supuestos!$B$35-L7) -> 3 | L8: =L7+K8 -> 12 | M8: =L8*Supuestos!$B$14 -> 206880 | N8: =M8*Supuestos!$B$29 -> 7114.8101 | O8: =K8*Supuestos!$B$23 -> 240000 | P8: =Supuestos!$B$26 -> 51000 | Q8: =M8-N8-O8-P8 -> -91234.81 | R8: =R7+Q8 -> -8664587 | T8: =MIN(Supuestos!$B$34, Supuestos!$B$35-U7) -> 6 | U8: =U7+T8 -> 24 | V8: =U8*Supuestos!$B$14 -> 413760 | W8: =V8*Supuestos!$B$29 -> 14229.62 | X8: =T8*Supuestos!$B$23 -> 480000 | Y8: =Supuestos!$B$26 -> 51000 | Z8: =V8-W8-X8-Y8 -> -131469.62 | AA8: =AA7+Z8 -> -9125174.1
A9: 5 | B9: =MIN(Supuestos!$B$32, Supuestos!$B$35-C8) -> 1 | C9: =C8+B9 -> 5 | D9: =C9*Supuestos!$B$14 -> 86200 | E9: =D9*Supuestos!$B$29 -> 2964.5042 | F9: =B9*Supuestos!$B$23 -> 80000 | G9: =Supuestos!$B$26 -> 51000 | H9: =D9-E9-F9-G9 -> -47764.504 | I9: =I8+H9 -> -8405293.5 | K9: =MIN(Supuestos!$B$33, Supuestos!$B$35-L8) -> 3 | L9: =L8+K9 -> 15 | M9: =L9*Supuestos!$B$14 -> 258600 | N9: =M9*Supuestos!$B$29 -> 8893.5126 | O9: =K9*Supuestos!$B$23 -> 240000 | P9: =Supuestos!$B$26 -> 51000 | Q9: =M9-N9-O9-P9 -> -41293.513 | R9: =R8+Q9 -> -8705880.5 | T9: =MIN(Supuestos!$B$34, Supuestos!$B$35-U8) -> 6 | U9: =U8+T9 -> 30 | V9: =U9*Supuestos!$B$14 -> 517200 | W9: =V9*Supuestos!$B$29 -> 17787.025 | X9: =T9*Supuestos!$B$23 -> 480000 | Y9: =Supuestos!$B$26 -> 51000 | Z9: =V9-W9-X9-Y9 -> -31587.025 | AA9: =AA8+Z9 -> -9156761.1
A10: 6 | B10: =MIN(Supuestos!$B$32, Supuestos!$B$35-C9) -> 1 | C10: =C9+B10 -> 6 | D10: =C10*Supuestos!$B$14 -> 103440 | E10: =D10*Supuestos!$B$29 -> 3557.405 | F10: =B10*Supuestos!$B$23 -> 80000 | G10: =Supuestos!$B$26 -> 51000 | H10: =D10-E10-F10-G10 -> -31117.405 | I10: =I9+H10 -> -8436410.9 | K10: =MIN(Supuestos!$B$33, Supuestos!$B$35-L9) -> 3 | L10: =L9+K10 -> 18 | M10: =L10*Supuestos!$B$14 -> 310320 | N10: =M10*Supuestos!$B$29 -> 10672.215 | O10: =K10*Supuestos!$B$23 -> 240000 | P10: =Supuestos!$B$26 -> 51000 | Q10: =M10-N10-O10-P10 -> 8647.7849 | R10: =R9+Q10 -> -8697232.8 | T10: =MIN(Supuestos!$B$34, Supuestos!$B$35-U9) -> 6 | U10: =U9+T10 -> 36 | V10: =U10*Supuestos!$B$14 -> 620640 | W10: =V10*Supuestos!$B$29 -> 21344.43 | X10: =T10*Supuestos!$B$23 -> 480000 | Y10: =Supuestos!$B$26 -> 51000 | Z10: =V10-W10-X10-Y10 -> 68295.57 | AA10: =AA9+Z10 -> -9088465.5
A11: 7 | B11: =MIN(Supuestos!$B$32, Supuestos!$B$35-C10) -> 1 | C11: =C10+B11 -> 7 | D11: =C11*Supuestos!$B$14 -> 120680 | E11: =D11*Supuestos!$B$29 -> 4150.3059 | F11: =B11*Supuestos!$B$23 -> 80000 | G11: =Supuestos!$B$26 -> 51000 | H11: =D11-E11-F11-G11 -> -14470.306 | I11: =I10+H11 -> -8450881.2 | K11: =MIN(Supuestos!$B$33, Supuestos!$B$35-L10) -> 3 | L11: =L10+K11 -> 21 | M11: =L11*Supuestos!$B$14 -> 362040 | N11: =M11*Supuestos!$B$29 -> 12450.918 | O11: =K11*Supuestos!$B$23 -> 240000 | P11: =Supuestos!$B$26 -> 51000 | Q11: =M11-N11-O11-P11 -> 58589.082 | R11: =R10+Q11 -> -8638643.7 | T11: =MIN(Supuestos!$B$34, Supuestos!$B$35-U10) -> 6 | U11: =U10+T11 -> 42 | V11: =U11*Supuestos!$B$14 -> 724080 | W11: =V11*Supuestos!$B$29 -> 24901.835 | X11: =T11*Supuestos!$B$23 -> 480000 | Y11: =Supuestos!$B$26 -> 51000 | Z11: =V11-W11-X11-Y11 -> 168178.16 | AA11: =AA10+Z11 -> -8920287.3
A12: 8 | B12: =MIN(Supuestos!$B$32, Supuestos!$B$35-C11) -> 1 | C12: =C11+B12 -> 8 | D12: =C12*Supuestos!$B$14 -> 137920 | E12: =D12*Supuestos!$B$29 -> 4743.2067 | F12: =B12*Supuestos!$B$23 -> 80000 | G12: =Supuestos!$B$26 -> 51000 | H12: =D12-E12-F12-G12 -> 2176.7933 | I12: =I11+H12 -> -8448704.4 | K12: =MIN(Supuestos!$B$33, Supuestos!$B$35-L11) -> 3 | L12: =L11+K12 -> 24 | M12: =L12*Supuestos!$B$14 -> 413760 | N12: =M12*Supuestos!$B$29 -> 14229.62 | O12: =K12*Supuestos!$B$23 -> 240000 | P12: =Supuestos!$B$26 -> 51000 | Q12: =M12-N12-O12-P12 -> 108530.38 | R12: =R11+Q12 -> -8530113.3 | T12: =MIN(Supuestos!$B$34, Supuestos!$B$35-U11) -> 6 | U12: =U11+T12 -> 48 | V12: =U12*Supuestos!$B$14 -> 827520 | W12: =V12*Supuestos!$B$29 -> 28459.24 | X12: =T12*Supuestos!$B$23 -> 480000 | Y12: =Supuestos!$B$26 -> 51000 | Z12: =V12-W12-X12-Y12 -> 268060.76 | AA12: =AA11+Z12 -> -8652226.6
A13: 9 | B13: =MIN(Supuestos!$B$32, Supuestos!$B$35-C12) -> 1 | C13: =C12+B13 -> 9 | D13: =C13*Supuestos!$B$14 -> 155160 | E13: =D13*Supuestos!$B$29 -> 5336.1076 | F13: =B13*Supuestos!$B$23 -> 80000 | G13: =Supuestos!$B$26 -> 51000 | H13: =D13-E13-F13-G13 -> 18823.892 | I13: =I12+H13 -> -8429880.5 | K13: =MIN(Supuestos!$B$33, Supuestos!$B$35-L12) -> 3 | L13: =L12+K13 -> 27 | M13: =L13*Supuestos!$B$14 -> 465480 | N13: =M13*Supuestos!$B$29 -> 16008.323 | O13: =K13*Supuestos!$B$23 -> 240000 | P13: =Supuestos!$B$26 -> 51000 | Q13: =M13-N13-O13-P13 -> 158471.68 | R13: =R12+Q13 -> -8371641.6 | T13: =MIN(Supuestos!$B$34, Supuestos!$B$35-U12) -> 6 | U13: =U12+T13 -> 54 | V13: =U13*Supuestos!$B$14 -> 930960 | W13: =V13*Supuestos!$B$29 -> 32016.645 | X13: =T13*Supuestos!$B$23 -> 480000 | Y13: =Supuestos!$B$26 -> 51000 | Z13: =V13-W13-X13-Y13 -> 367943.35 | AA13: =AA12+Z13 -> -8284283.2
A14: 10 | B14: =MIN(Supuestos!$B$32, Supuestos!$B$35-C13) -> 1 | C14: =C13+B14 -> 10 | D14: =C14*Supuestos!$B$14 -> 172400 | E14: =D14*Supuestos!$B$29 -> 5929.0084 | F14: =B14*Supuestos!$B$23 -> 80000 | G14: =Supuestos!$B$26 -> 51000 | H14: =D14-E14-F14-G14 -> 35470.992 | I14: =I13+H14 -> -8394409.5 | K14: =MIN(Supuestos!$B$33, Supuestos!$B$35-L13) -> 3 | L14: =L13+K14 -> 30 | M14: =L14*Supuestos!$B$14 -> 517200 | N14: =M14*Supuestos!$B$29 -> 17787.025 | O14: =K14*Supuestos!$B$23 -> 240000 | P14: =Supuestos!$B$26 -> 51000 | Q14: =M14-N14-O14-P14 -> 208412.97 | R14: =R13+Q14 -> -8163228.6 | T14: =MIN(Supuestos!$B$34, Supuestos!$B$35-U13) -> 6 | U14: =U13+T14 -> 60 | V14: =U14*Supuestos!$B$14 -> 1034400 | W14: =V14*Supuestos!$B$29 -> 35574.05 | X14: =T14*Supuestos!$B$23 -> 480000 | Y14: =Supuestos!$B$26 -> 51000 | Z14: =V14-W14-X14-Y14 -> 467825.95 | AA14: =AA13+Z14 -> -7816457.3
A15: 11 | B15: =MIN(Supuestos!$B$32, Supuestos!$B$35-C14) -> 1 | C15: =C14+B15 -> 11 | D15: =C15*Supuestos!$B$14 -> 189640 | E15: =D15*Supuestos!$B$29 -> 6521.9092 | F15: =B15*Supuestos!$B$23 -> 80000 | G15: =Supuestos!$B$26 -> 51000 | H15: =D15-E15-F15-G15 -> 52118.091 | I15: =I14+H15 -> -8342291.5 | K15: =MIN(Supuestos!$B$33, Supuestos!$B$35-L14) -> 3 | L15: =L14+K15 -> 33 | M15: =L15*Supuestos!$B$14 -> 568920 | N15: =M15*Supuestos!$B$29 -> 19565.728 | O15: =K15*Supuestos!$B$23 -> 240000 | P15: =Supuestos!$B$26 -> 51000 | Q15: =M15-N15-O15-P15 -> 258354.27 | R15: =R14+Q15 -> -7904874.4 | T15: =MIN(Supuestos!$B$34, Supuestos!$B$35-U14) -> 6 | U15: =U14+T15 -> 66 | V15: =U15*Supuestos!$B$14 -> 1137840 | W15: =V15*Supuestos!$B$29 -> 39131.455 | X15: =T15*Supuestos!$B$23 -> 480000 | Y15: =Supuestos!$B$26 -> 51000 | Z15: =V15-W15-X15-Y15 -> 567708.54 | AA15: =AA14+Z15 -> -7248748.7
A16: 12 | B16: =MIN(Supuestos!$B$32, Supuestos!$B$35-C15) -> 1 | C16: =C15+B16 -> 12 | D16: =C16*Supuestos!$B$14 -> 206880 | E16: =D16*Supuestos!$B$29 -> 7114.8101 | F16: =B16*Supuestos!$B$23 -> 80000 | G16: =Supuestos!$B$26 -> 51000 | H16: =D16-E16-F16-G16 -> 68765.19 | I16: =I15+H16 -> -8273526.3 | K16: =MIN(Supuestos!$B$33, Supuestos!$B$35-L15) -> 3 | L16: =L15+K16 -> 36 | M16: =L16*Supuestos!$B$14 -> 620640 | N16: =M16*Supuestos!$B$29 -> 21344.43 | O16: =K16*Supuestos!$B$23 -> 240000 | P16: =Supuestos!$B$26 -> 51000 | Q16: =M16-N16-O16-P16 -> 308295.57 | R16: =R15+Q16 -> -7596578.8 | T16: =MIN(Supuestos!$B$34, Supuestos!$B$35-U15) -> 6 | U16: =U15+T16 -> 72 | V16: =U16*Supuestos!$B$14 -> 1241280 | W16: =V16*Supuestos!$B$29 -> 42688.86 | X16: =T16*Supuestos!$B$23 -> 480000 | Y16: =Supuestos!$B$26 -> 51000 | Z16: =V16-W16-X16-Y16 -> 667591.14 | AA16: =AA15+Z16 -> -6581157.6
... A64: 60 | B64: =MIN(Supuestos!$B$32, Supuestos!$B$35-C63) -> 1 | C64: =C63+B64 -> 60 | D64: =C64*Supuestos!$B$14 -> 1034400 | E64: =D64*Supuestos!$B$29 -> 35574.05 | F64: =B64*Supuestos!$B$23 -> 80000 | G64: =Supuestos!$B$26 -> 51000 | H64: =D64-E64-F64-G64 -> 867825.95 | I64: =I63+H64 -> 14604191 | K64: =MIN(Supuestos!$B$33, Supuestos!$B$35-L63) -> 0 | L64: =L63+K64 -> 100 | M64: =L64*Supuestos!$B$14 -> 1724000 | N64: =M64*Supuestos!$B$29 -> 59290.084 | O64: =K64*Supuestos!$B$23 -> 0 | P64: =Supuestos!$B$26 -> 51000 | Q64: =M64-N64-O64-P64 -> 1613709.9 | R64: =R63+Q64 -> 53904236 | T64: =MIN(Supuestos!$B$34, Supuestos!$B$35-U63) -> 0 | U64: =U63+T64 -> 100 | V64: =U64*Supuestos!$B$14 -> 1724000 | W64: =V64*Supuestos!$B$29 -> 59290.084 | X64: =T64*Supuestos!$B$23 -> 0 | Y64: =Supuestos!$B$26 -> 51000 | Z64: =V64-W64-X64-Y64 -> 1613709.9 | AA64: =AA63+Z64 -> 67771269

Sheet Resumen
A1: WALKAN — Recuperación de inversión: resultados
A2: ¿En cuántos meses el flujo acumulado de Walkan vuelve a cero (payback)?
A4: Escenario | B4: Clientes nuevos/mes | C4: Mes de recuperación | D4: Flujo acumulado al mes 60 | E4: Ingreso mensual en régimen (100 clientes)
A5: Conservador | B5: =Supuestos!$B$32 -> 1 | C5: =IFERROR(_xlfn.MINIFS(Proyeccion!$A$5:$A$64,Proyeccion!$I$5:$I$64,">=0"),"No recupera en "&Supuestos!$B$36&" meses") -> 40 | D5: =Proyeccion!$I$64 -> 14604191 | E5: =Supuestos!$B$35*Supuestos!$B$14*(1-Supuestos!$B$29)-Supuestos!$B$26 -> 1613709.9
A6: Realista | B6: =Supuestos!$B$33 -> 3 | C6: =IFERROR(_xlfn.MINIFS(Proyeccion!$A$5:$A$64,Proyeccion!$R$5:$R$64,">=0"),"No recupera en "&Supuestos!$B$36&" meses") -> 25 | D6: =Proyeccion!$R$64 -> 53904236 | E6: =Supuestos!$B$35*Supuestos!$B$14*(1-Supuestos!$B$29)-Supuestos!$B$26 -> 1613709.9
A7: Optimista | B7: =Supuestos!$B$34 -> 6 | C7: =IFERROR(_xlfn.MINIFS(Proyeccion!$A$5:$A$64,Proyeccion!$AA$5:$AA$64,">=0"),"No recupera en "&Supuestos!$B$36&" meses") -> 19 | D7: =Proyeccion!$AA$64 -> 67771269 | E7: =Supuestos!$B$35*Supuestos!$B$14*(1-Supuestos!$B$29)-Supuestos!$B$26 -> 1613709.9
A9: Nota: el 'mes de recuperación' es el primer mes en que el flujo acumulado (ingresos − comisión Flow − hardware regalado − opex − inversión inicial) deja de ser negativo. Todos los supuestos son editables en la hoja Supuestos.
